git_search_replace-1.0.3.data/scripts/gsr-branch.py
gitsearchreplace/__init__.py
git_search_replace-1.0.3.dist-info/LICENSE.txt
git_search_replace-1.0.3.dist-info/METADATA
git_search_replace-1.0.3.dist-info/WHEEL
git_search_replace-1.0.3.dist-info/entry_points.txt
git_search_replace-1.0.3.dist-info/top_level.txt
git_search_replace-1.0.3.dist-info/RECORD
