Metadata-Version: 2.1
Name: git-search-replace
Version: 1.0.3
Summary: a utility on top of git for project-wide search-and-replace that includes filenames too
Home-page: https://github.com/da-x/git-search-replace
Author: Dan Aloni
Author-email: alonid@gmail.com
License: LICENSE.txt
Platform: UNKNOWN
Classifier: Programming Language :: Python
Classifier: Programming Language :: Python :: 3.0
Classifier: License :: OSI Approved :: BSD License
Requires-Dist: plumbum (>=1.5)
